agentlens/__init__.py
agentlens/core.py
agentlens/terminal.py
agentlens/integrations/__init__.py
agentlens/integrations/langchain.py
agentlens/integrations/openai.py
auriel_agentlens-0.1.1.dist-info/METADATA
auriel_agentlens-0.1.1.dist-info/WHEEL
auriel_agentlens-0.1.1.dist-info/entry_points.txt
auriel_agentlens-0.1.1.dist-info/licenses/LICENSE
auriel_agentlens-0.1.1.dist-info/RECORD
