Metadata-Version: 2.4
Name: auriel-agentlens
Version: 0.1.1
Summary: An open-source offline AI agent debugging tool: record, replay, analyze failures, and track API costs—free and local.
Author: Jack Dolby
License: MIT
License-File: LICENSE
Requires-Dist: click
Requires-Dist: rich
Provides-Extra: dev
Requires-Dist: black; extra == 'dev'
Requires-Dist: mypy; extra == 'dev'
Requires-Dist: pre-commit; extra == 'dev'
Requires-Dist: pytest; extra == 'dev'
Requires-Dist: pytest-asyncio; extra == 'dev'
Requires-Dist: pytest-cov; extra == 'dev'
Requires-Dist: ruff; extra == 'dev'
Provides-Extra: langchain
Requires-Dist: langchain; extra == 'langchain'
Provides-Extra: openai
Requires-Dist: openai; extra == 'openai'
